python_datapack/__init__.py
python_datapack/constants.py
python_datapack/enhance_config.py
python_datapack/finalyze.py
python_datapack/initialize.py
python_datapack/verify_database.py
python_datapack/datapack/basic_structure.py
python_datapack/datapack/custom_block_ticks.py
python_datapack/datapack/custom_blocks.py
python_datapack/datapack/headers.py
python_datapack/datapack/lang.py
python_datapack/datapack/loading.py
python_datapack/datapack/loot_tables.py
python_datapack/datapack/main.py
python_datapack/datapack/recipes.py
python_datapack/manual/book_optimizer.py
python_datapack/manual/main.py
python_datapack/manual/shared_import.py
python_datapack/manual/utils.py
python_datapack/manual/assets/furnace.png
python_datapack/manual/assets/invisible_item.png
python_datapack/manual/assets/invisible_item_release.png
python_datapack/manual/assets/minecraft_font.ttf
python_datapack/manual/assets/none.png
python_datapack/manual/assets/none_release.png
python_datapack/manual/assets/shaped_2x2.png
python_datapack/manual/assets/shaped_3x3.png
python_datapack/manual/assets/simple_case_no_border.png
python_datapack/manual/assets/wiki_information.png
python_datapack/manual/assets/wiki_ingredient_of_craft.png
python_datapack/manual/assets/wiki_ingredient_of_craft_template.png
python_datapack/manual/assets/wiki_result_of_craft.png
python_datapack/resource_pack/check_unused_textures.py
python_datapack/resource_pack/item_models.py
python_datapack/resource_pack/main.py
python_datapack/resource_pack/sounds.py
python_datapack/resource_pack/vanilla_models.py
python_datapack/utils/cache.py
python_datapack/utils/database_helper.py
python_datapack/utils/ingredients.py
python_datapack/utils/io.py
python_datapack/utils/multiprocessing.py
python_datapack/utils/print.py
python_datapack/utils/weld.py
python_datapack-0.2.7.dist-info/METADATA
python_datapack-0.2.7.dist-info/WHEEL
python_datapack-0.2.7.dist-info/licenses/LICENSE
python_datapack-0.2.7.dist-info/RECORD
