Metadata-Version: 2.3
Name: python_datapack
Version: 0.2.7
Summary: Python package to help generating advanced Minecraft datapack contents
Project-URL: Homepage, https://github.com/Stoupy51/python_datapack
Project-URL: Issues, https://github.com/Stoupy51/python_datapack/issues
Author-email: Stoupy51 <stoupy51@gmail.com>
License-File: LICENSE
Classifier: License :: OSI Approved :: MIT License
Classifier: Operating System :: OS Independent
Classifier: Programming Language :: Python :: 3
Requires-Python: >=3.10
